{
  "album_id": "72177720332095960",
  "account": "primary",
  "created_at": "2026-02-20T00:18:27.366215",
  "last_update": "2026-02-26T09:32:34.931681",
  "total_photos": 192,
  "posted_count": 20,
  "failed_count": 0,
  "pending_count": 0,
  "retrying_count": 0,
  "completion_status": "active",
  "completion_percentage": 10.416666666666668,
  "last_posted_position": 20,
  "last_posted_at": "2026-02-26T07:40:57.046952",
  "next_scheduled_position": null,
  "estimated_completion_date": null,
  "workflow_runs_count": 40,
  "last_workflow_run_id": "22432557406",
  "error_count": 0,
  "last_error_message": null,
  "last_error_at": null
}