[
  {
    "position": 1,
    "photo_id": "54585949706",
    "instagram_post_id": null,
    "facebook_post_id": null,
    "threads_post_id": null,
    "threads_posted_at": null,
    "threads_caption": null,
    "threads_retry_count": 0,
    "generated_body": null,
    "posted_at": null,
    "title": "Agli Amici Rovinj Amuse-Bouches",
    "status": "posted",
    "retry_count": 0,
    "workflow_run_id": "22249594276",
    "account": "secondary",
    "created_at": "2026-02-21T03:37:56.728133",
    "last_update": "2026-02-21T03:37:56.728139",
    "flickr_url": "https://live.staticflickr.com/65535/54585949706_8babcb6958_c.jpg",
    "instagram_url": null,
    "caption_length": null,
    "hashtags_count": null,
    "is_dry_run": true
  },
  {
    "position": 2,
    "photo_id": "54586139399",
    "instagram_post_id": null,
    "facebook_post_id": null,
    "threads_post_id": null,
    "threads_posted_at": null,
    "threads_caption": null,
    "threads_retry_count": 0,
    "generated_body": "The sommelier at Agli Amici Rovinj is heading our way, and I am already smiling. \ud83c\udf77\n\nThis is the only two-Michelin-star restaurant in all of Croatia, and every detail here feels intentional and alive.\n\nGrissini stand upright in a sleek black cylinder, a cracker rests in a ceramic snail holder, and a glass of white wine catches the light \u2014 this is how a meal begins here.\n\nOur sommelier has an almost telepathic sense for what we want, and honestly, we are laughing more than I expected at a fine dining table.\n\nAgli Amici Rovinj is the Istrian outpost of the Scarello family from Udine, and Michela Scarello herself is here today \u2014 on her vacation, no less.",
    "posted_at": null,
    "title": "Agli Amici Rovinj Gourmet Sommelier",
    "status": "posted",
    "retry_count": 0,
    "workflow_run_id": "29123285072",
    "account": "secondary",
    "created_at": "2026-07-10T21:00:27.501662",
    "last_update": "2026-07-10T21:00:27.501671",
    "flickr_url": "https://live.staticflickr.com/65535/54586139399_81af97990d_c.jpg",
    "instagram_url": null,
    "caption_length": null,
    "hashtags_count": null,
    "is_dry_run": true
  }
]